{
  "1397486522080428194": {
    "commission_message_id": "1397486525796712499",
    "thread": "1397486525796712499",
    "budget": "asd",
    "time_frame": "asd",
    "description": "asd"
  },
  "1397487394248200324": {
    "commission_message_id": "1397487397431939092",
    "thread": "1397487397431939092",
    "budget": "asd123",
    "time_frame": "asd",
    "description": "asd"
  },
  "1397547710592319629": {
    "commission_message_id": "1397547718661898351",
    "thread": "1397547718661898351",
    "budget": "$50",
    "time_frame": "1d",
    "description": "Test mobile"
  },
  "1397547966608445521": {
    "commission_message_id": "1397547969871347882",
    "thread": "1397547969871347882",
    "budget": "123",
    "time_frame": "Asd",
    "description": "Asd"
  }
}